iscasmodel/__init__.py
iscasmodel/core.py
iscasmodel/feng.py
iscasmodel/accelerate/__init__.py
iscasmodel/accelerate/accelerator.py
iscasmodel/accelerate/big_modeling.py
iscasmodel/accelerate/checkpointing.py
iscasmodel/accelerate/data_loader.py
iscasmodel/accelerate/hooks.py
iscasmodel/accelerate/launchers.py
iscasmodel/accelerate/local_sgd.py
iscasmodel/accelerate/logging.py
iscasmodel/accelerate/memory_utils.py
iscasmodel/accelerate/optimizer.py
iscasmodel/accelerate/scheduler.py
iscasmodel/accelerate/state.py
iscasmodel/accelerate/tracking.py
iscasmodel/accelerate/commands/__init__.py
iscasmodel/accelerate/commands/accelerate_cli.py
iscasmodel/accelerate/commands/env.py
iscasmodel/accelerate/commands/estimate.py
iscasmodel/accelerate/commands/launch.py
iscasmodel/accelerate/commands/test.py
iscasmodel/accelerate/commands/tpu.py
iscasmodel/accelerate/commands/config/__init__.py
iscasmodel/accelerate/commands/config/cluster.py
iscasmodel/accelerate/commands/config/config.py
iscasmodel/accelerate/commands/config/config_args.py
iscasmodel/accelerate/commands/config/config_utils.py
iscasmodel/accelerate/commands/config/default.py
iscasmodel/accelerate/commands/config/sagemaker.py
iscasmodel/accelerate/commands/config/update.py
iscasmodel/accelerate/commands/menu/__init__.py
iscasmodel/accelerate/commands/menu/cursor.py
iscasmodel/accelerate/commands/menu/helpers.py
iscasmodel/accelerate/commands/menu/input.py
iscasmodel/accelerate/commands/menu/keymap.py
iscasmodel/accelerate/commands/menu/selection_menu.py
iscasmodel/accelerate/test_utils/__init__.py
iscasmodel/accelerate/test_utils/examples.py
iscasmodel/accelerate/test_utils/testing.py
iscasmodel/accelerate/test_utils/training.py
iscasmodel/accelerate/test_utils/scripts/__init__.py
iscasmodel/accelerate/test_utils/scripts/test_cli.py
iscasmodel/accelerate/test_utils/scripts/test_distributed_data_loop.py
iscasmodel/accelerate/test_utils/scripts/test_notebook.py
iscasmodel/accelerate/test_utils/scripts/test_ops.py
iscasmodel-0.36.dist-info/METADATA
iscasmodel-0.36.dist-info/WHEEL
iscasmodel-0.36.dist-info/top_level.txt
iscasmodel-0.36.dist-info/RECORD
