Metadata-Version: 2.1
Name: iscasmodel
Version: 0.36
Summary: A library to send accuracy data
Home-page: https://github.com/yourusername/mylibrary
Author: ls
Author-email: your.email@example.com
Requires-Dist: requests
Requires-Dist: torch (==2.0.0)
